[
	{
		"rowcount": "1",
		"officeenum": "1",
		"id": "MarkWebb",
		"name": "Mark Webb",
		"title": "Congregational Leader",
		"imagefile": "leader.jpg",
		"iconfile": "leader-icon.jpg",
		"email": "mark@livingmessiah.com",
		"biofile": "leader.md"
	},
	{
		"rowcount": "2",
		"officeenum": "2",
		"id": "RalphieCratty",
		"name": "Ralphie Cratty",
		"title": "Beit Din",
		"imagefile": "beit-din-1.jpg",
		"iconfile": "beit-din-1-icon.jpg",
		"email": "ralphie@livingmessiah.com",
		"biofile": "BietDien1.md"
	},
	//{
	//	"rowcount": "3",
	//	"officeenum": "3",
	//	"id": "JerryWatkins",
	//	"name": "Jerry Watkins",
	//	"title": "Beit Din",
	//	"imagefile": "beit-din-2.jpg",
	//	"iconfile": "beit-din-2-icon.jpg",
	//	"email": "Jerry@livingmessiah.com",
	//	"biofile": "BietDien2.md"
	//},
	{
		"rowcount": "4",
		"officeenum": "4",
		"id": "JohnMarsing",
		"name": "John Marsing",
		"title": "Beit Din",
		"imagefile": "beit-din-3.jpg",
		"iconfile": "beit-din-3-icon.jpg",
		"email": "John@livingmessiah.com",
		"biofile": "BietDien3.md"
	},
	{
		"rowcount": "5",
		"officeenum": "5",
		"id": "PatShackleford",
		"name": "Pat Shackleford",
		"title": "Elder",
		"imagefile": "elder-1.jpg",
		"iconfile": "elder-1-icon.jpg",
		"email": "Pat@livingmessiah.com",
		"biofile": "Elder1.md"
	},
	{
		"rowcount": "6",
		"officeenum": "6",
		"id": "DaveScherer",
		"name": "Dave Scherer",
		"title": "Elder",
		"imagefile": "elder-2.jpg",
		"iconfile": "elder-2-icon.jpg",
		"email": "Dave@livingmessiah.com",
		"biofile": "Elder2.md"
	},
	{
		"rowcount": "7",
		"officeenum": "7",
		"id": "PaulHebron",
		"name": "PaulHebron",
		"title": "Elder",
		"imagefile": "elder-3.jpg",
		"iconfile": "elder-3-icon.jpg",
		"email": "Paul@livingmessiah.com",
		"biofile": "Elder3.md"
	}
	// whebron@gmail.com
	//{
	//	"rowcount": "7",
	//	"officeenum": "7",
	//	"id": "ChrisLengyel",
	//	"name": "Chris Lengyel",
	//	"title": "Music Leader",
	//	"imagefile": "music-leader.jpg",
	//	"iconfile": "music-leader-icon.jpg",
	//	"email": "Chris@livingmessiah.com",
	//	"partialview": "_MusicLeader",
	//	"biofile": "Elder2.md"
	//}
	]
